shipyard_templates/__init__.py
shipyard_templates/cloudstorage.py
shipyard_templates/crm.py
shipyard_templates/database.py
shipyard_templates/datavisualization.py
shipyard_templates/digital_advertising.py
shipyard_templates/documents.py
shipyard_templates/errors.py
shipyard_templates/etl.py
shipyard_templates/exit_code_exception.py
shipyard_templates/messaging.py
shipyard_templates/notebooks.py
shipyard_templates/projectmanagement.py
shipyard_templates/shipyard_logger.py
shipyard_templates/spreadsheets.py
shipyard_templates-0.10.0.dist-info/METADATA
shipyard_templates-0.10.0.dist-info/WHEEL
shipyard_templates-0.10.0.dist-info/top_level.txt
shipyard_templates-0.10.0.dist-info/RECORD
