Metadata-Version: 2.4
Name: shipyard-templates
Version: 0.10.0
Summary: Super classes for blueprint development
Requires-Python: >=3.11
